datapage/__init__.py
datapage/__main__.py
tests/__init__.py
datapage-0.0.1.dist-info/METADATA
datapage-0.0.1.dist-info/WHEEL
datapage-0.0.1.dist-info/entry_points.txt
datapage-0.0.1.dist-info/top_level.txt
datapage-0.0.1.dist-info/RECORD
