Metadata-Version: 2.1
Name: datapage
Version: 0.0.1
Summary: Cool Python app built with Pyrustic
Home-page: https://github.com/pyrustic/datapage
Author: Pyrustic Evangelist
Author-email: rusticalex@yahoo.com
Maintainer: Pyrustic Evangelist
Maintainer-email: rusticalex@yahoo.com
License: MIT
Keywords: application
Platform: UNKNOWN
Classifier: Programming Language :: Python :: 3
Classifier: License :: OSI Approved :: MIT License
Classifier: Operating System :: OS Independent
Requires-Python: >=3.5
Requires-Dist: shared
Requires-Dist: backstage
